{
    "DNDConfig": null,
    "_height_": {
        "type": "string",
        "value": "220dp"
    },
    "_left_": {
        "type": "string",
        "value": "0"
    },
    "_margin_": [
        0,
        0,
        0,
        0
    ],
    "_orientation_": 6,
    "_padding_": [
        0,
        0,
        0,
        0
    ],
    "_percent_": true,
    "_skin_": "se321420f0b5497f989421b39d377e4e",
    "_top_": {
        "type": "string",
        "value": "5%"
    },
    "_width_": {
        "type": "string",
        "value": "100%"
    },
    "allboxes": [],
    "canUpdateUI": true,
    "children": [
        "flxWorksheetName",
        "flxFileName"
    ],
    "clipbounds": false,
    "containerweight": 100,
    "enablescrolling": true,
    "id": "flxOutputDetails",
    "info": null,
    "iscustomlayout": false,
    "isvisible": true,
    "kuid": "a7842c2f86ab42e783fab7aba1b747c4",
    "layouttype": 4,
    "name": "kony.ui.FlexContainer",
    "parent": "flxExportSide",
    "pf": "frmMain",
    "retaincontentalignment": false,
    "retainflexpositionproperties": false,
    "retainflowhorizontalalignment": false,
    "snapgridsize": 10,
    "snaptogrid": true,
    "wType": "FlexContainer",
    "widgetalignment": 1
}